pyflaarum/__init__.py
pyflaarum/objects.py
pyflaarum/statements.py
pyflaarum-1.3.0.dist-info/LICENSE
pyflaarum-1.3.0.dist-info/METADATA
pyflaarum-1.3.0.dist-info/WHEEL
pyflaarum-1.3.0.dist-info/top_level.txt
pyflaarum-1.3.0.dist-info/RECORD
