Metadata-Version: 2.1
Name: pyflaarum
Version: 1.3.0
Summary: A library to interact with flaarum database
Author-email: Bankole Ojo <ojobankole@gmail.com>
Project-URL: Homepage, https://sae.ng/flaarumtuts/
Project-URL: Issues, https://github.com/saenuma/pyflaarum/issues
Classifier: Programming Language :: Python :: 3
Classifier: License :: OSI Approved :: MIT License
Classifier: Operating System :: OS Independent
Requires-Python: >=3.8
License-File: LICENSE
